azfs/__init__.py
azfs/az_file_client.py
azfs/az_file_system.py
azfs/error.py
azfs/utils.py
azfs/cli/__init__.py
azfs/cli/constants.py
azfs/cli/factory.py
azfs/clients/__init__.py
azfs/clients/blob_client.py
azfs/clients/client_interface.py
azfs/clients/datalake_client.py
azfs/clients/queue_client.py
azfs/table_storage/__init__.py
azfs/table_storage/table_storage.py
test/__init__.py
test/conftest.py
test/export_decorator_example.py
test/test_blob_client.py
test/test_cli.py
test/test_clients.py
test/test_datalake_client.py
test/test_queue_client.py
test/test_table_storage.py
test/test_utils.py
azfs-0.2.14.dist-info/LICENSE
azfs-0.2.14.dist-info/METADATA
azfs-0.2.14.dist-info/WHEEL
azfs-0.2.14.dist-info/entry_points.txt
azfs-0.2.14.dist-info/top_level.txt
azfs-0.2.14.dist-info/RECORD
