Metadata-Version: 2.1
Name: azfs
Version: 0.2.14
Summary: AzFS is to provide convenient Python read/write functions for Azure Storage Account.
Home-page: https://github.com/gsy0911/azfs
Author: gsy0911
Author-email: yoshiki0911@gmail.com
License: MIT
Project-URL: Bug Tracker, https://github.com/gsy0911/azfs/issues
Project-URL: Documentation, https://azfs.readthedocs.io/en/latest/?badge=latest
Project-URL: Source Code, https://github.com/gsy0911/azfs
Keywords: Azure,StorageAccount,Blob,DataLake,Queue
Platform: UNKNOWN
Classifier: Programming Language :: Python :: 3
Classifier: Programming Language :: Python :: 3.6
Classifier: Programming Language :: Python :: 3.7
Classifier: Programming Language :: Python :: 3.8
Classifier: Development Status :: 3 - Alpha
Classifier: Operating System :: OS Independent
Classifier: Intended Audience :: Developers
Classifier: License :: OSI Approved :: MIT License
Requires-Python: >=3.6
Requires-Dist: pandas
Requires-Dist: azure-cosmosdb-table
Requires-Dist: azure-identity (>=1.3.1)
Requires-Dist: azure-storage-blob (>=12.3.0)
Requires-Dist: azure-storage-file-datalake (>=12.0.0)
Requires-Dist: azure-storage-queue (>=12.1.1)
Requires-Dist: fsspec
Requires-Dist: click
